{
    "Meta Data": {
        "1. Information": "Daily Prices (open, high, low, close) and Volumes",
        "2. Symbol": "FTHY",
        "3. Last Refreshed": "2021-04-16",
        "4. Output Size": "Full size",
        "5. Time Zone": "US/Eastern"
    },
    "Time Series (Daily)": {
        "2021-04-16": {
            "1. open": "20.0500",
            "2. high": "20.1900",
            "3. low": "20.0220",
            "4. close": "20.0800",
            "5. volume": "69043"
        },
        "2021-04-15": {
            "1. open": "20.0000",
            "2. high": "20.2000",
            "3. low": "19.9800",
            "4. close": "20.1100",
            "5. volume": "111893"
        },
        "2021-04-14": {
            "1. open": "19.8800",
            "2. high": "20.0500",
            "3. low": "19.8800",
            "4. close": "20.0000",
            "5. volume": "47309"
        },
        "2021-04-13": {
            "1. open": "19.9600",
            "2. high": "20.0684",
            "3. low": "19.8600",
            "4. close": "19.9300",
            "5. volume": "51161"
        },
        "2021-04-12": {
            "1. open": "20.1000",
            "2. high": "20.1200",
            "3. low": "19.9542",
            "4. close": "20.0200",
            "5. volume": "85666"
        },
        "2021-04-09": {
            "1. open": "20.0600",
            "2. high": "20.1200",
            "3. low": "19.9568",
            "4. close": "20.1000",
            "5. volume": "154977"
        },
        "2021-04-08": {
            "1. open": "19.9700",
            "2. high": "20.0600",
            "3. low": "19.9100",
            "4. close": "19.9900",
            "5. volume": "51866"
        },
        "2021-04-07": {
            "1. open": "19.8600",
            "2. high": "19.9900",
            "3. low": "19.7500",
            "4. close": "19.9100",
            "5. volume": "84173"
        },
        "2021-04-06": {
            "1. open": "19.9700",
            "2. high": "20.0500",
            "3. low": "19.8400",
            "4. close": "19.9600",
            "5. volume": "52403"
        },
        "2021-04-05": {
            "1. open": "19.8600",
            "2. high": "20.0000",
            "3. low": "19.8300",
            "4. close": "19.8600",
            "5. volume": "43240"
        },
        "2021-04-01": {
            "1. open": "19.8200",
            "2. high": "19.8900",
            "3. low": "19.7400",
            "4. close": "19.8900",
            "5. volume": "52884"
        },
        "2021-03-31": {
            "1. open": "19.6300",
            "2. high": "19.8500",
            "3. low": "19.6300",
            "4. close": "19.8500",
            "5. volume": "83262"
        },
        "2021-03-30": {
            "1. open": "19.5700",
            "2. high": "19.7100",
            "3. low": "19.5501",
            "4. close": "19.7100",
            "5. volume": "67926"
        },
        "2021-03-29": {
            "1. open": "19.5700",
            "2. high": "19.6500",
            "3. low": "19.4500",
            "4. close": "19.5800",
            "5. volume": "70244"
        },
        "2021-03-26": {
            "1. open": "19.3200",
            "2. high": "19.5700",
            "3. low": "19.3200",
            "4. close": "19.5500",
            "5. volume": "91157"
        },
        "2021-03-25": {
            "1. open": "19.4300",
            "2. high": "19.5500",
            "3. low": "19.2900",
            "4. close": "19.4000",
            "5. volume": "143754"
        },
        "2021-03-24": {
            "1. open": "19.7000",
            "2. high": "19.7400",
            "3. low": "19.4200",
            "4. close": "19.4800",
            "5. volume": "233988"
        },
        "2021-03-23": {
            "1. open": "19.6800",
            "2. high": "19.7500",
            "3. low": "19.4600",
            "4. close": "19.6000",
            "5. volume": "141228"
        },
        "2021-03-22": {
            "1. open": "19.5500",
            "2. high": "19.7900",
            "3. low": "19.5500",
            "4. close": "19.7300",
            "5. volume": "127757"
        },
        "2021-03-19": {
            "1. open": "19.4400",
            "2. high": "19.6400",
            "3. low": "19.4400",
            "4. close": "19.5500",
            "5. volume": "124926"
        },
        "2021-03-18": {
            "1. open": "19.4100",
            "2. high": "19.6481",
            "3. low": "19.4100",
            "4. close": "19.5100",
            "5. volume": "94531"
        },
        "2021-03-17": {
            "1. open": "19.6000",
            "2. high": "19.8000",
            "3. low": "19.5000",
            "4. close": "19.6800",
            "5. volume": "84034"
        },
        "2021-03-16": {
            "1. open": "19.6000",
            "2. high": "19.8000",
            "3. low": "19.5800",
            "4. close": "19.7200",
            "5. volume": "123349"
        },
        "2021-03-15": {
            "1. open": "19.6400",
            "2. high": "19.7000",
            "3. low": "19.5300",
            "4. close": "19.6500",
            "5. volume": "92749"
        },
        "2021-03-12": {
            "1. open": "19.5100",
            "2. high": "19.6000",
            "3. low": "19.5000",
            "4. close": "19.5800",
            "5. volume": "92732"
        },
        "2021-03-11": {
            "1. open": "19.8000",
            "2. high": "19.8200",
            "3. low": "19.4900",
            "4. close": "19.5600",
            "5. volume": "114182"
        },
        "2021-03-10": {
            "1. open": "19.6500",
            "2. high": "19.8000",
            "3. low": "19.6000",
            "4. close": "19.6000",
            "5. volume": "117871"
        },
        "2021-03-09": {
            "1. open": "19.6300",
            "2. high": "19.7499",
            "3. low": "19.5400",
            "4. close": "19.7000",
            "5. volume": "100363"
        },
        "2021-03-08": {
            "1. open": "19.6900",
            "2. high": "19.8100",
            "3. low": "19.6000",
            "4. close": "19.6800",
            "5. volume": "109347"
        },
        "2021-03-05": {
            "1. open": "19.8000",
            "2. high": "19.9382",
            "3. low": "19.5450",
            "4. close": "19.7800",
            "5. volume": "77880"
        },
        "2021-03-04": {
            "1. open": "19.9900",
            "2. high": "20.0000",
            "3. low": "19.7000",
            "4. close": "19.8500",
            "5. volume": "55280"
        },
        "2021-03-03": {
            "1. open": "19.8723",
            "2. high": "20.0000",
            "3. low": "19.7600",
            "4. close": "20.0000",
            "5. volume": "59956"
        },
        "2021-03-02": {
            "1. open": "19.8700",
            "2. high": "20.0000",
            "3. low": "19.7100",
            "4. close": "19.8100",
            "5. volume": "131305"
        },
        "2021-03-01": {
            "1. open": "19.7400",
            "2. high": "20.0000",
            "3. low": "19.7400",
            "4. close": "19.9900",
            "5. volume": "47209"
        },
        "2021-02-26": {
            "1. open": "19.9500",
            "2. high": "20.0300",
            "3. low": "19.7700",
            "4. close": "19.7900",
            "5. volume": "106102"
        },
        "2021-02-25": {
            "1. open": "20.0000",
            "2. high": "20.0500",
            "3. low": "19.7100",
            "4. close": "20.0000",
            "5. volume": "191151"
        },
        "2021-02-24": {
            "1. open": "19.9400",
            "2. high": "20.0750",
            "3. low": "19.8600",
            "4. close": "19.9600",
            "5. volume": "211761"
        },
        "2021-02-23": {
            "1. open": "20.0700",
            "2. high": "20.2000",
            "3. low": "19.7700",
            "4. close": "19.9000",
            "5. volume": "130965"
        },
        "2021-02-22": {
            "1. open": "19.9000",
            "2. high": "20.1000",
            "3. low": "19.7700",
            "4. close": "20.0200",
            "5. volume": "172611"
        },
        "2021-02-19": {
            "1. open": "19.9000",
            "2. high": "20.1000",
            "3. low": "19.9000",
            "4. close": "20.0000",
            "5. volume": "153733"
        },
        "2021-02-18": {
            "1. open": "20.0900",
            "2. high": "20.0900",
            "3. low": "19.3700",
            "4. close": "19.8700",
            "5. volume": "200705"
        },
        "2021-02-17": {
            "1. open": "20.0300",
            "2. high": "20.3700",
            "3. low": "19.7000",
            "4. close": "20.0700",
            "5. volume": "150478"
        },
        "2021-02-16": {
            "1. open": "19.7800",
            "2. high": "20.0500",
            "3. low": "19.6300",
            "4. close": "20.0100",
            "5. volume": "245065"
        },
        "2021-02-12": {
            "1. open": "19.8480",
            "2. high": "19.9200",
            "3. low": "19.7500",
            "4. close": "19.8500",
            "5. volume": "111326"
        },
        "2021-02-11": {
            "1. open": "19.9200",
            "2. high": "20.0800",
            "3. low": "19.7500",
            "4. close": "19.8700",
            "5. volume": "103331"
        },
        "2021-02-10": {
            "1. open": "19.9000",
            "2. high": "20.1000",
            "3. low": "19.7400",
            "4. close": "20.0000",
            "5. volume": "122240"
        },
        "2021-02-09": {
            "1. open": "19.7100",
            "2. high": "20.1500",
            "3. low": "19.7100",
            "4. close": "19.9200",
            "5. volume": "319974"
        },
        "2021-02-08": {
            "1. open": "19.8500",
            "2. high": "19.9000",
            "3. low": "19.7000",
            "4. close": "19.7400",
            "5. volume": "94235"
        },
        "2021-02-05": {
            "1. open": "19.9000",
            "2. high": "19.9000",
            "3. low": "19.7000",
            "4. close": "19.7700",
            "5. volume": "73409"
        },
        "2021-02-04": {
            "1. open": "19.8200",
            "2. high": "19.9700",
            "3. low": "19.6600",
            "4. close": "19.7800",
            "5. volume": "85672"
        },
        "2021-02-03": {
            "1. open": "19.8300",
            "2. high": "19.9900",
            "3. low": "19.5300",
            "4. close": "19.9000",
            "5. volume": "127539"
        },
        "2021-02-02": {
            "1. open": "19.6000",
            "2. high": "19.8500",
            "3. low": "19.5800",
            "4. close": "19.7400",
            "5. volume": "96836"
        },
        "2021-02-01": {
            "1. open": "19.5100",
            "2. high": "19.7800",
            "3. low": "19.4200",
            "4. close": "19.6500",
            "5. volume": "113709"
        },
        "2021-01-29": {
            "1. open": "19.8100",
            "2. high": "19.8100",
            "3. low": "19.4100",
            "4. close": "19.6000",
            "5. volume": "165401"
        },
        "2021-01-28": {
            "1. open": "19.7100",
            "2. high": "20.0000",
            "3. low": "19.6900",
            "4. close": "19.7800",
            "5. volume": "60218"
        },
        "2021-01-27": {
            "1. open": "19.6700",
            "2. high": "19.8900",
            "3. low": "19.5300",
            "4. close": "19.7600",
            "5. volume": "108119"
        },
        "2021-01-26": {
            "1. open": "19.5500",
            "2. high": "19.8900",
            "3. low": "19.4700",
            "4. close": "19.8100",
            "5. volume": "187244"
        },
        "2021-01-25": {
            "1. open": "19.7300",
            "2. high": "19.8400",
            "3. low": "19.5100",
            "4. close": "19.6100",
            "5. volume": "96281"
        },
        "2021-01-22": {
            "1. open": "19.4100",
            "2. high": "19.6800",
            "3. low": "19.2800",
            "4. close": "19.6700",
            "5. volume": "215644"
        },
        "2021-01-21": {
            "1. open": "19.4200",
            "2. high": "19.6000",
            "3. low": "19.3200",
            "4. close": "19.4000",
            "5. volume": "230174"
        },
        "2021-01-20": {
            "1. open": "19.5000",
            "2. high": "19.7500",
            "3. low": "19.4000",
            "4. close": "19.5200",
            "5. volume": "222008"
        },
        "2021-01-19": {
            "1. open": "19.5800",
            "2. high": "19.7800",
            "3. low": "19.4202",
            "4. close": "19.4600",
            "5. volume": "120554"
        },
        "2021-01-15": {
            "1. open": "19.6400",
            "2. high": "19.8500",
            "3. low": "19.5400",
            "4. close": "19.5800",
            "5. volume": "90411"
        },
        "2021-01-14": {
            "1. open": "19.7100",
            "2. high": "19.7999",
            "3. low": "19.5500",
            "4. close": "19.7500",
            "5. volume": "117095"
        },
        "2021-01-13": {
            "1. open": "19.7500",
            "2. high": "19.9000",
            "3. low": "19.6300",
            "4. close": "19.7400",
            "5. volume": "144358"
        },
        "2021-01-12": {
            "1. open": "19.8800",
            "2. high": "19.9200",
            "3. low": "19.7200",
            "4. close": "19.8500",
            "5. volume": "88445"
        },
        "2021-01-11": {
            "1. open": "19.7000",
            "2. high": "19.9800",
            "3. low": "19.6600",
            "4. close": "19.9300",
            "5. volume": "221014"
        },
        "2021-01-08": {
            "1. open": "19.9100",
            "2. high": "20.1100",
            "3. low": "19.8500",
            "4. close": "19.9300",
            "5. volume": "109117"
        },
        "2021-01-07": {
            "1. open": "19.9000",
            "2. high": "20.0800",
            "3. low": "19.9000",
            "4. close": "19.9300",
            "5. volume": "68168"
        },
        "2021-01-06": {
            "1. open": "19.8200",
            "2. high": "20.0900",
            "3. low": "19.8000",
            "4. close": "19.8700",
            "5. volume": "63555"
        },
        "2021-01-05": {
            "1. open": "20.0700",
            "2. high": "20.0800",
            "3. low": "19.8400",
            "4. close": "19.9100",
            "5. volume": "62036"
        },
        "2021-01-04": {
            "1. open": "20.2700",
            "2. high": "20.2700",
            "3. low": "19.9001",
            "4. close": "19.9800",
            "5. volume": "38796"
        },
        "2020-12-31": {
            "1. open": "20.1000",
            "2. high": "20.4000",
            "3. low": "20.1000",
            "4. close": "20.3200",
            "5. volume": "38629"
        },
        "2020-12-30": {
            "1. open": "19.8100",
            "2. high": "20.1600",
            "3. low": "19.8100",
            "4. close": "20.1000",
            "5. volume": "30656"
        },
        "2020-12-29": {
            "1. open": "19.9300",
            "2. high": "20.1800",
            "3. low": "19.9100",
            "4. close": "19.9600",
            "5. volume": "87884"
        },
        "2020-12-28": {
            "1. open": "20.2000",
            "2. high": "20.3990",
            "3. low": "19.9000",
            "4. close": "19.9200",
            "5. volume": "64023"
        },
        "2020-12-24": {
            "1. open": "20.1000",
            "2. high": "20.2000",
            "3. low": "20.0600",
            "4. close": "20.1900",
            "5. volume": "25218"
        },
        "2020-12-23": {
            "1. open": "20.1800",
            "2. high": "20.2900",
            "3. low": "20.0638",
            "4. close": "20.1100",
            "5. volume": "43911"
        },
        "2020-12-22": {
            "1. open": "20.1000",
            "2. high": "20.3999",
            "3. low": "20.0500",
            "4. close": "20.2200",
            "5. volume": "62214"
        },
        "2020-12-21": {
            "1. open": "20.4000",
            "2. high": "20.4000",
            "3. low": "20.0300",
            "4. close": "20.1000",
            "5. volume": "71525"
        },
        "2020-12-18": {
            "1. open": "20.3600",
            "2. high": "20.5000",
            "3. low": "20.3600",
            "4. close": "20.4100",
            "5. volume": "44069"
        },
        "2020-12-17": {
            "1. open": "20.4500",
            "2. high": "20.4999",
            "3. low": "20.3400",
            "4. close": "20.3900",
            "5. volume": "79103"
        },
        "2020-12-16": {
            "1. open": "20.4400",
            "2. high": "20.4400",
            "3. low": "20.1600",
            "4. close": "20.4000",
            "5. volume": "108110"
        },
        "2020-12-15": {
            "1. open": "20.3401",
            "2. high": "20.4500",
            "3. low": "20.1800",
            "4. close": "20.3400",
            "5. volume": "57330"
        },
        "2020-12-14": {
            "1. open": "20.0800",
            "2. high": "20.3179",
            "3. low": "20.0750",
            "4. close": "20.1800",
            "5. volume": "40766"
        },
        "2020-12-11": {
            "1. open": "20.2700",
            "2. high": "20.3000",
            "3. low": "19.9100",
            "4. close": "19.9700",
            "5. volume": "114972"
        },
        "2020-12-10": {
            "1. open": "19.8600",
            "2. high": "20.3200",
            "3. low": "19.7500",
            "4. close": "20.3200",
            "5. volume": "123228"
        },
        "2020-12-09": {
            "1. open": "20.1500",
            "2. high": "20.1500",
            "3. low": "19.7800",
            "4. close": "19.9300",
            "5. volume": "213203"
        },
        "2020-12-08": {
            "1. open": "20.1300",
            "2. high": "20.2400",
            "3. low": "20.0000",
            "4. close": "20.1500",
            "5. volume": "131217"
        },
        "2020-12-07": {
            "1. open": "19.8200",
            "2. high": "20.1500",
            "3. low": "19.8200",
            "4. close": "20.0700",
            "5. volume": "89671"
        },
        "2020-12-04": {
            "1. open": "19.9200",
            "2. high": "20.0000",
            "3. low": "19.8300",
            "4. close": "19.8800",
            "5. volume": "48469"
        },
        "2020-12-03": {
            "1. open": "19.7700",
            "2. high": "20.0000",
            "3. low": "19.7700",
            "4. close": "19.8100",
            "5. volume": "49903"
        },
        "2020-12-02": {
            "1. open": "19.7400",
            "2. high": "20.0000",
            "3. low": "19.7400",
            "4. close": "19.8500",
            "5. volume": "40294"
        },
        "2020-12-01": {
            "1. open": "19.7200",
            "2. high": "20.0000",
            "3. low": "19.7200",
            "4. close": "19.7700",
            "5. volume": "68818"
        },
        "2020-11-30": {
            "1. open": "20.0000",
            "2. high": "20.1400",
            "3. low": "19.8000",
            "4. close": "19.8400",
            "5. volume": "109149"
        },
        "2020-11-27": {
            "1. open": "19.7600",
            "2. high": "20.0000",
            "3. low": "19.7500",
            "4. close": "19.9500",
            "5. volume": "61125"
        },
        "2020-11-25": {
            "1. open": "20.0000",
            "2. high": "20.1500",
            "3. low": "19.6300",
            "4. close": "19.7800",
            "5. volume": "106260"
        },
        "2020-11-24": {
            "1. open": "19.9000",
            "2. high": "20.0000",
            "3. low": "19.7000",
            "4. close": "19.9500",
            "5. volume": "95835"
        },
        "2020-11-23": {
            "1. open": "20.0000",
            "2. high": "20.0000",
            "3. low": "19.8600",
            "4. close": "19.9200",
            "5. volume": "50383"
        },
        "2020-11-20": {
            "1. open": "19.7800",
            "2. high": "20.0000",
            "3. low": "19.5510",
            "4. close": "19.9200",
            "5. volume": "96891"
        },
        "2020-11-19": {
            "1. open": "19.8000",
            "2. high": "19.9700",
            "3. low": "19.6500",
            "4. close": "19.9300",
            "5. volume": "45571"
        },
        "2020-11-18": {
            "1. open": "19.6300",
            "2. high": "19.8320",
            "3. low": "19.5600",
            "4. close": "19.6800",
            "5. volume": "100390"
        },
        "2020-11-17": {
            "1. open": "19.8000",
            "2. high": "20.1500",
            "3. low": "19.4600",
            "4. close": "19.6000",
            "5. volume": "122545"
        },
        "2020-11-16": {
            "1. open": "19.8200",
            "2. high": "20.1160",
            "3. low": "19.6500",
            "4. close": "19.7400",
            "5. volume": "76638"
        },
        "2020-11-13": {
            "1. open": "19.9100",
            "2. high": "20.5510",
            "3. low": "19.9100",
            "4. close": "19.9500",
            "5. volume": "72990"
        },
        "2020-11-12": {
            "1. open": "20.2000",
            "2. high": "20.2000",
            "3. low": "19.7800",
            "4. close": "20.0100",
            "5. volume": "62773"
        },
        "2020-11-11": {
            "1. open": "19.9700",
            "2. high": "20.1000",
            "3. low": "19.8200",
            "4. close": "20.0305",
            "5. volume": "52031"
        },
        "2020-11-10": {
            "1. open": "19.7500",
            "2. high": "20.0000",
            "3. low": "19.7500",
            "4. close": "19.9900",
            "5. volume": "60319"
        },
        "2020-11-09": {
            "1. open": "19.7800",
            "2. high": "19.7800",
            "3. low": "19.4100",
            "4. close": "19.7500",
            "5. volume": "118370"
        },
        "2020-11-06": {
            "1. open": "19.3500",
            "2. high": "19.9965",
            "3. low": "19.3500",
            "4. close": "19.7900",
            "5. volume": "65761"
        },
        "2020-11-05": {
            "1. open": "19.7000",
            "2. high": "19.9480",
            "3. low": "19.3700",
            "4. close": "19.4300",
            "5. volume": "118485"
        },
        "2020-11-04": {
            "1. open": "19.6960",
            "2. high": "19.7300",
            "3. low": "19.5200",
            "4. close": "19.5200",
            "5. volume": "40518"
        },
        "2020-11-03": {
            "1. open": "19.7200",
            "2. high": "19.8323",
            "3. low": "19.6000",
            "4. close": "19.6100",
            "5. volume": "39444"
        },
        "2020-11-02": {
            "1. open": "20.1000",
            "2. high": "20.1000",
            "3. low": "19.6700",
            "4. close": "19.6700",
            "5. volume": "46173"
        },
        "2020-10-30": {
            "1. open": "19.8000",
            "2. high": "20.1155",
            "3. low": "19.6500",
            "4. close": "20.0300",
            "5. volume": "56711"
        },
        "2020-10-29": {
            "1. open": "19.6900",
            "2. high": "20.0900",
            "3. low": "19.6900",
            "4. close": "19.9600",
            "5. volume": "46585"
        },
        "2020-10-28": {
            "1. open": "20.2200",
            "2. high": "20.3500",
            "3. low": "19.6000",
            "4. close": "19.6900",
            "5. volume": "103775"
        },
        "2020-10-27": {
            "1. open": "20.3800",
            "2. high": "20.6000",
            "3. low": "20.1000",
            "4. close": "20.4200",
            "5. volume": "73708"
        },
        "2020-10-26": {
            "1. open": "20.3000",
            "2. high": "20.6000",
            "3. low": "20.1600",
            "4. close": "20.2300",
            "5. volume": "50580"
        },
        "2020-10-23": {
            "1. open": "20.4142",
            "2. high": "20.6000",
            "3. low": "20.3100",
            "4. close": "20.4000",
            "5. volume": "43653"
        },
        "2020-10-22": {
            "1. open": "20.1600",
            "2. high": "20.4700",
            "3. low": "20.1000",
            "4. close": "20.3500",
            "5. volume": "59372"
        },
        "2020-10-21": {
            "1. open": "20.0900",
            "2. high": "20.3500",
            "3. low": "20.0900",
            "4. close": "20.2500",
            "5. volume": "32365"
        },
        "2020-10-20": {
            "1. open": "20.5400",
            "2. high": "20.5400",
            "3. low": "20.0538",
            "4. close": "20.1700",
            "5. volume": "39710"
        },
        "2020-10-19": {
            "1. open": "20.2900",
            "2. high": "20.6000",
            "3. low": "20.1100",
            "4. close": "20.5400",
            "5. volume": "153715"
        },
        "2020-10-16": {
            "1. open": "20.3576",
            "2. high": "20.5400",
            "3. low": "20.1980",
            "4. close": "20.3300",
            "5. volume": "37780"
        },
        "2020-10-15": {
            "1. open": "20.2500",
            "2. high": "20.5800",
            "3. low": "20.1301",
            "4. close": "20.4700",
            "5. volume": "38404"
        },
        "2020-10-14": {
            "1. open": "20.1400",
            "2. high": "20.4911",
            "3. low": "20.0653",
            "4. close": "20.2600",
            "5. volume": "30255"
        },
        "2020-10-13": {
            "1. open": "20.4000",
            "2. high": "20.4400",
            "3. low": "19.9500",
            "4. close": "20.0600",
            "5. volume": "78817"
        },
        "2020-10-12": {
            "1. open": "20.1500",
            "2. high": "20.4400",
            "3. low": "20.1500",
            "4. close": "20.2900",
            "5. volume": "62855"
        },
        "2020-10-09": {
            "1. open": "20.2800",
            "2. high": "20.4680",
            "3. low": "20.1800",
            "4. close": "20.1800",
            "5. volume": "20034"
        },
        "2020-10-08": {
            "1. open": "20.4000",
            "2. high": "20.5670",
            "3. low": "20.2100",
            "4. close": "20.2100",
            "5. volume": "39333"
        },
        "2020-10-07": {
            "1. open": "20.2972",
            "2. high": "20.4900",
            "3. low": "20.2500",
            "4. close": "20.2500",
            "5. volume": "22537"
        },
        "2020-10-06": {
            "1. open": "20.6000",
            "2. high": "20.6500",
            "3. low": "20.2500",
            "4. close": "20.3900",
            "5. volume": "98681"
        },
        "2020-10-05": {
            "1. open": "20.7700",
            "2. high": "20.7700",
            "3. low": "20.3000",
            "4. close": "20.5980",
            "5. volume": "23771"
        },
        "2020-10-02": {
            "1. open": "20.2300",
            "2. high": "20.7000",
            "3. low": "20.1011",
            "4. close": "20.6000",
            "5. volume": "44440"
        },
        "2020-10-01": {
            "1. open": "20.0300",
            "2. high": "20.5000",
            "3. low": "20.0300",
            "4. close": "20.4800",
            "5. volume": "95037"
        },
        "2020-09-30": {
            "1. open": "20.1400",
            "2. high": "20.4000",
            "3. low": "20.0200",
            "4. close": "20.1518",
            "5. volume": "76790"
        },
        "2020-09-29": {
            "1. open": "19.9800",
            "2. high": "20.2800",
            "3. low": "19.6450",
            "4. close": "20.2100",
            "5. volume": "58649"
        },
        "2020-09-28": {
            "1. open": "19.6800",
            "2. high": "20.0000",
            "3. low": "19.6000",
            "4. close": "20.0000",
            "5. volume": "46247"
        },
        "2020-09-25": {
            "1. open": "20.0000",
            "2. high": "20.0000",
            "3. low": "19.5100",
            "4. close": "19.6000",
            "5. volume": "71902"
        },
        "2020-09-24": {
            "1. open": "19.9800",
            "2. high": "20.3100",
            "3. low": "19.9072",
            "4. close": "20.0000",
            "5. volume": "54029"
        },
        "2020-09-23": {
            "1. open": "20.7100",
            "2. high": "20.7100",
            "3. low": "19.8400",
            "4. close": "19.9800",
            "5. volume": "118106"
        },
        "2020-09-22": {
            "1. open": "20.7900",
            "2. high": "20.7900",
            "3. low": "20.1500",
            "4. close": "20.2400",
            "5. volume": "42920"
        },
        "2020-09-21": {
            "1. open": "21.0000",
            "2. high": "21.0000",
            "3. low": "20.3100",
            "4. close": "20.3100",
            "5. volume": "80211"
        },
        "2020-09-18": {
            "1. open": "20.5200",
            "2. high": "20.6000",
            "3. low": "20.4100",
            "4. close": "20.5300",
            "5. volume": "39217"
        },
        "2020-09-17": {
            "1. open": "20.5100",
            "2. high": "20.7500",
            "3. low": "20.3000",
            "4. close": "20.6400",
            "5. volume": "56625"
        },
        "2020-09-16": {
            "1. open": "20.1000",
            "2. high": "20.6500",
            "3. low": "20.0800",
            "4. close": "20.4000",
            "5. volume": "53051"
        },
        "2020-09-15": {
            "1. open": "20.1400",
            "2. high": "20.6200",
            "3. low": "20.0600",
            "4. close": "20.1500",
            "5. volume": "67385"
        },
        "2020-09-14": {
            "1. open": "20.3200",
            "2. high": "20.4000",
            "3. low": "20.1400",
            "4. close": "20.2600",
            "5. volume": "66119"
        },
        "2020-09-11": {
            "1. open": "20.1900",
            "2. high": "20.2500",
            "3. low": "20.0700",
            "4. close": "20.1800",
            "5. volume": "32554"
        },
        "2020-09-10": {
            "1. open": "20.2400",
            "2. high": "20.3300",
            "3. low": "19.5950",
            "4. close": "20.0000",
            "5. volume": "82373"
        },
        "2020-09-09": {
            "1. open": "20.1400",
            "2. high": "20.4500",
            "3. low": "20.1000",
            "4. close": "20.2000",
            "5. volume": "56051"
        },
        "2020-09-08": {
            "1. open": "20.3100",
            "2. high": "20.3100",
            "3. low": "20.0500",
            "4. close": "20.0700",
            "5. volume": "40525"
        },
        "2020-09-04": {
            "1. open": "20.3400",
            "2. high": "20.5000",
            "3. low": "20.0100",
            "4. close": "20.3100",
            "5. volume": "90183"
        },
        "2020-09-03": {
            "1. open": "20.9600",
            "2. high": "20.9600",
            "3. low": "20.3400",
            "4. close": "20.3400",
            "5. volume": "68729"
        },
        "2020-09-02": {
            "1. open": "21.0000",
            "2. high": "21.0935",
            "3. low": "20.6100",
            "4. close": "20.9600",
            "5. volume": "89136"
        },
        "2020-09-01": {
            "1. open": "21.1300",
            "2. high": "21.1300",
            "3. low": "20.0100",
            "4. close": "21.0000",
            "5. volume": "98876"
        },
        "2020-08-31": {
            "1. open": "20.7300",
            "2. high": "21.1235",
            "3. low": "20.7300",
            "4. close": "21.0600",
            "5. volume": "52201"
        },
        "2020-08-28": {
            "1. open": "20.8000",
            "2. high": "20.9000",
            "3. low": "20.6000",
            "4. close": "20.9000",
            "5. volume": "58690"
        },
        "2020-08-27": {
            "1. open": "20.5500",
            "2. high": "20.8000",
            "3. low": "20.5500",
            "4. close": "20.7300",
            "5. volume": "59154"
        },
        "2020-08-26": {
            "1. open": "20.8700",
            "2. high": "20.8700",
            "3. low": "20.4572",
            "4. close": "20.6900",
            "5. volume": "66559"
        },
        "2020-08-25": {
            "1. open": "20.7600",
            "2. high": "20.9000",
            "3. low": "20.7200",
            "4. close": "20.8000",
            "5. volume": "49751"
        },
        "2020-08-24": {
            "1. open": "20.9000",
            "2. high": "20.9900",
            "3. low": "20.7600",
            "4. close": "20.8300",
            "5. volume": "52732"
        },
        "2020-08-21": {
            "1. open": "20.7400",
            "2. high": "21.0000",
            "3. low": "20.6050",
            "4. close": "20.9050",
            "5. volume": "79018"
        },
        "2020-08-20": {
            "1. open": "20.7500",
            "2. high": "20.8300",
            "3. low": "20.4600",
            "4. close": "20.7300",
            "5. volume": "103790"
        },
        "2020-08-19": {
            "1. open": "21.0000",
            "2. high": "21.0000",
            "3. low": "20.6900",
            "4. close": "20.7500",
            "5. volume": "70103"
        },
        "2020-08-18": {
            "1. open": "20.7500",
            "2. high": "20.9900",
            "3. low": "20.6750",
            "4. close": "20.9500",
            "5. volume": "61536"
        },
        "2020-08-17": {
            "1. open": "20.7400",
            "2. high": "21.3500",
            "3. low": "20.6300",
            "4. close": "20.8700",
            "5. volume": "121533"
        },
        "2020-08-14": {
            "1. open": "20.8200",
            "2. high": "21.0000",
            "3. low": "20.6600",
            "4. close": "20.7100",
            "5. volume": "97888"
        },
        "2020-08-13": {
            "1. open": "20.6300",
            "2. high": "21.0000",
            "3. low": "20.4802",
            "4. close": "21.0000",
            "5. volume": "99810"
        },
        "2020-08-12": {
            "1. open": "20.9500",
            "2. high": "20.9500",
            "3. low": "20.1800",
            "4. close": "20.3900",
            "5. volume": "139954"
        },
        "2020-08-11": {
            "1. open": "20.6200",
            "2. high": "20.9500",
            "3. low": "20.5670",
            "4. close": "20.9100",
            "5. volume": "130633"
        },
        "2020-08-10": {
            "1. open": "20.8100",
            "2. high": "20.9500",
            "3. low": "20.5050",
            "4. close": "20.6500",
            "5. volume": "99093"
        },
        "2020-08-07": {
            "1. open": "21.0000",
            "2. high": "21.0000",
            "3. low": "20.6300",
            "4. close": "20.6300",
            "5. volume": "91878"
        },
        "2020-08-06": {
            "1. open": "21.3100",
            "2. high": "21.3100",
            "3. low": "20.7000",
            "4. close": "20.9400",
            "5. volume": "101820"
        },
        "2020-08-05": {
            "1. open": "20.6000",
            "2. high": "21.1000",
            "3. low": "20.4700",
            "4. close": "21.0500",
            "5. volume": "105862"
        },
        "2020-08-04": {
            "1. open": "20.6000",
            "2. high": "20.7900",
            "3. low": "20.4650",
            "4. close": "20.5782",
            "5. volume": "91502"
        },
        "2020-08-03": {
            "1. open": "20.3700",
            "2. high": "20.6000",
            "3. low": "20.1100",
            "4. close": "20.4762",
            "5. volume": "81509"
        },
        "2020-07-31": {
            "1. open": "20.0000",
            "2. high": "20.3400",
            "3. low": "20.0000",
            "4. close": "20.3100",
            "5. volume": "99609"
        },
        "2020-07-30": {
            "1. open": "20.4600",
            "2. high": "20.4600",
            "3. low": "20.0100",
            "4. close": "20.0375",
            "5. volume": "114247"
        },
        "2020-07-29": {
            "1. open": "20.0600",
            "2. high": "20.1000",
            "3. low": "20.0000",
            "4. close": "20.0660",
            "5. volume": "126250"
        },
        "2020-07-28": {
            "1. open": "20.6000",
            "2. high": "20.6100",
            "3. low": "20.0600",
            "4. close": "20.0700",
            "5. volume": "160145"
        },
        "2020-07-27": {
            "1. open": "21.0000",
            "2. high": "21.1000",
            "3. low": "20.6000",
            "4. close": "20.6000",
            "5. volume": "271308"
        },
        "2020-07-24": {
            "1. open": "21.2000",
            "2. high": "21.7999",
            "3. low": "21.2000",
            "4. close": "21.7200",
            "5. volume": "69746"
        },
        "2020-07-23": {
            "1. open": "21.2500",
            "2. high": "21.2500",
            "3. low": "20.9575",
            "4. close": "21.1651",
            "5. volume": "115640"
        },
        "2020-07-22": {
            "1. open": "21.0600",
            "2. high": "21.2000",
            "3. low": "20.7900",
            "4. close": "20.9700",
            "5. volume": "122081"
        },
        "2020-07-21": {
            "1. open": "20.8100",
            "2. high": "21.2000",
            "3. low": "20.7300",
            "4. close": "20.9500",
            "5. volume": "143646"
        },
        "2020-07-20": {
            "1. open": "21.1200",
            "2. high": "21.2000",
            "3. low": "20.7500",
            "4. close": "20.9100",
            "5. volume": "63226"
        },
        "2020-07-17": {
            "1. open": "21.2200",
            "2. high": "21.3000",
            "3. low": "20.9770",
            "4. close": "21.0600",
            "5. volume": "101673"
        },
        "2020-07-16": {
            "1. open": "21.1000",
            "2. high": "21.2500",
            "3. low": "21.0200",
            "4. close": "21.2200",
            "5. volume": "88216"
        },
        "2020-07-15": {
            "1. open": "20.7000",
            "2. high": "21.2400",
            "3. low": "20.6000",
            "4. close": "21.1600",
            "5. volume": "147542"
        },
        "2020-07-14": {
            "1. open": "20.6400",
            "2. high": "20.7500",
            "3. low": "20.4500",
            "4. close": "20.6300",
            "5. volume": "153280"
        },
        "2020-07-13": {
            "1. open": "20.7500",
            "2. high": "20.8000",
            "3. low": "20.6600",
            "4. close": "20.6600",
            "5. volume": "95241"
        },
        "2020-07-10": {
            "1. open": "20.7000",
            "2. high": "20.7600",
            "3. low": "20.5700",
            "4. close": "20.6400",
            "5. volume": "76769"
        },
        "2020-07-09": {
            "1. open": "20.9500",
            "2. high": "20.9500",
            "3. low": "20.5800",
            "4. close": "20.6500",
            "5. volume": "98481"
        },
        "2020-07-08": {
            "1. open": "20.7000",
            "2. high": "20.9400",
            "3. low": "20.6270",
            "4. close": "20.9000",
            "5. volume": "131570"
        },
        "2020-07-07": {
            "1. open": "20.6300",
            "2. high": "20.7500",
            "3. low": "20.5500",
            "4. close": "20.7300",
            "5. volume": "124428"
        },
        "2020-07-06": {
            "1. open": "20.5700",
            "2. high": "20.6500",
            "3. low": "20.4860",
            "4. close": "20.6200",
            "5. volume": "130390"
        },
        "2020-07-02": {
            "1. open": "20.4500",
            "2. high": "20.5840",
            "3. low": "20.3900",
            "4. close": "20.4900",
            "5. volume": "106265"
        },
        "2020-07-01": {
            "1. open": "20.2500",
            "2. high": "20.5000",
            "3. low": "20.1500",
            "4. close": "20.4300",
            "5. volume": "214596"
        },
        "2020-06-30": {
            "1. open": "20.2500",
            "2. high": "20.2900",
            "3. low": "20.1600",
            "4. close": "20.2200",
            "5. volume": "103235"
        },
        "2020-06-29": {
            "1. open": "20.0500",
            "2. high": "20.2760",
            "3. low": "20.0100",
            "4. close": "20.1800",
            "5. volume": "426784"
        },
        "2020-06-26": {
            "1. open": "20.0000",
            "2. high": "20.0900",
            "3. low": "20.0000",
            "4. close": "20.0000",
            "5. volume": "1927805"
        }
    }
}