{
    "Meta Data": {
        "1. Information": "Daily Prices (open, high, low, close) and Volumes",
        "2. Symbol": "OCFCP",
        "3. Last Refreshed": "2021-04-21",
        "4. Output Size": "Full size",
        "5. Time Zone": "US/Eastern"
    },
    "Time Series (Daily)": {
        "2021-04-21": {
            "1. open": "28.2615",
            "2. high": "28.9000",
            "3. low": "28.0000",
            "4. close": "28.0000",
            "5. volume": "1600"
        },
        "2021-04-20": {
            "1. open": "27.8500",
            "2. high": "27.8500",
            "3. low": "27.8500",
            "4. close": "27.8500",
            "5. volume": "0"
        },
        "2021-04-19": {
            "1. open": "27.8500",
            "2. high": "27.8500",
            "3. low": "27.8500",
            "4. close": "27.8500",
            "5. volume": "790"
        },
        "2021-04-16": {
            "1. open": "27.8500",
            "2. high": "27.8500",
            "3. low": "27.8499",
            "4. close": "27.8500",
            "5. volume": "600"
        },
        "2021-04-15": {
            "1. open": "27.8500",
            "2. high": "27.8500",
            "3. low": "27.8500",
            "4. close": "27.8500",
            "5. volume": "306"
        },
        "2021-04-14": {
            "1. open": "27.8500",
            "2. high": "27.8500",
            "3. low": "27.1000",
            "4. close": "27.5000",
            "5. volume": "1700"
        },
        "2021-04-13": {
            "1. open": "27.8500",
            "2. high": "27.8500",
            "3. low": "27.8500",
            "4. close": "27.8500",
            "5. volume": "0"
        },
        "2021-04-12": {
            "1. open": "27.8500",
            "2. high": "27.8500",
            "3. low": "27.8500",
            "4. close": "27.8500",
            "5. volume": "0"
        },
        "2021-04-09": {
            "1. open": "27.8100",
            "2. high": "27.8500",
            "3. low": "27.8100",
            "4. close": "27.8500",
            "5. volume": "850"
        },
        "2021-04-08": {
            "1. open": "27.8500",
            "2. high": "27.8500",
            "3. low": "27.8500",
            "4. close": "27.8500",
            "5. volume": "200"
        },
        "2021-04-07": {
            "1. open": "27.8400",
            "2. high": "27.8400",
            "3. low": "27.8000",
            "4. close": "27.8400",
            "5. volume": "900"
        },
        "2021-04-06": {
            "1. open": "27.7200",
            "2. high": "27.8500",
            "3. low": "27.6000",
            "4. close": "27.8500",
            "5. volume": "11125"
        },
        "2021-04-05": {
            "1. open": "27.5700",
            "2. high": "27.7900",
            "3. low": "27.5000",
            "4. close": "27.7200",
            "5. volume": "6714"
        },
        "2021-04-01": {
            "1. open": "27.7569",
            "2. high": "27.7569",
            "3. low": "27.4900",
            "4. close": "27.5400",
            "5. volume": "2100"
        },
        "2021-03-31": {
            "1. open": "27.1986",
            "2. high": "27.7900",
            "3. low": "27.1986",
            "4. close": "27.4400",
            "5. volume": "3511"
        },
        "2021-03-30": {
            "1. open": "27.6900",
            "2. high": "27.7800",
            "3. low": "27.5500",
            "4. close": "27.5500",
            "5. volume": "400"
        },
        "2021-03-29": {
            "1. open": "27.6700",
            "2. high": "27.7400",
            "3. low": "27.6700",
            "4. close": "27.7400",
            "5. volume": "400"
        },
        "2021-03-26": {
            "1. open": "27.2500",
            "2. high": "27.4800",
            "3. low": "27.2400",
            "4. close": "27.4000",
            "5. volume": "7500"
        },
        "2021-03-25": {
            "1. open": "27.5000",
            "2. high": "27.7892",
            "3. low": "27.5000",
            "4. close": "27.7000",
            "5. volume": "1746"
        },
        "2021-03-24": {
            "1. open": "27.2600",
            "2. high": "27.7400",
            "3. low": "27.2300",
            "4. close": "27.5000",
            "5. volume": "11090"
        },
        "2021-03-23": {
            "1. open": "27.7900",
            "2. high": "27.7900",
            "3. low": "27.7900",
            "4. close": "27.7900",
            "5. volume": "500"
        },
        "2021-03-22": {
            "1. open": "27.8400",
            "2. high": "27.8400",
            "3. low": "27.2702",
            "4. close": "27.2702",
            "5. volume": "1771"
        },
        "2021-03-19": {
            "1. open": "27.6000",
            "2. high": "27.7500",
            "3. low": "27.1878",
            "4. close": "27.1878",
            "5. volume": "685"
        },
        "2021-03-18": {
            "1. open": "27.4000",
            "2. high": "27.4000",
            "3. low": "27.4000",
            "4. close": "27.4000",
            "5. volume": "200000"
        },
        "2021-03-17": {
            "1. open": "27.4000",
            "2. high": "27.4000",
            "3. low": "27.4000",
            "4. close": "27.4000",
            "5. volume": "0"
        },
        "2021-03-16": {
            "1. open": "27.4000",
            "2. high": "27.4000",
            "3. low": "27.4000",
            "4. close": "27.4000",
            "5. volume": "8"
        },
        "2021-03-15": {
            "1. open": "27.1200",
            "2. high": "27.5600",
            "3. low": "27.0777",
            "4. close": "27.4000",
            "5. volume": "5819"
        },
        "2021-03-12": {
            "1. open": "27.3000",
            "2. high": "27.3000",
            "3. low": "27.3000",
            "4. close": "27.3000",
            "5. volume": "0"
        },
        "2021-03-11": {
            "1. open": "27.1000",
            "2. high": "27.3000",
            "3. low": "27.0700",
            "4. close": "27.3000",
            "5. volume": "4947"
        },
        "2021-03-10": {
            "1. open": "27.0000",
            "2. high": "27.2790",
            "3. low": "26.9600",
            "4. close": "27.0673",
            "5. volume": "4500"
        },
        "2021-03-09": {
            "1. open": "27.5500",
            "2. high": "27.7900",
            "3. low": "27.4300",
            "4. close": "27.4300",
            "5. volume": "2220"
        },
        "2021-03-08": {
            "1. open": "27.7900",
            "2. high": "27.7900",
            "3. low": "27.3421",
            "4. close": "27.3500",
            "5. volume": "5131"
        },
        "2021-03-05": {
            "1. open": "27.3000",
            "2. high": "27.3000",
            "3. low": "27.3000",
            "4. close": "27.3000",
            "5. volume": "602"
        },
        "2021-03-04": {
            "1. open": "27.5500",
            "2. high": "27.5500",
            "3. low": "27.5500",
            "4. close": "27.5500",
            "5. volume": "754"
        },
        "2021-03-03": {
            "1. open": "27.0000",
            "2. high": "27.4200",
            "3. low": "27.0000",
            "4. close": "27.4200",
            "5. volume": "290"
        },
        "2021-03-02": {
            "1. open": "27.3500",
            "2. high": "27.3500",
            "3. low": "27.3500",
            "4. close": "27.3500",
            "5. volume": "2"
        },
        "2021-03-01": {
            "1. open": "27.2600",
            "2. high": "27.3500",
            "3. low": "27.2500",
            "4. close": "27.3500",
            "5. volume": "732"
        },
        "2021-02-26": {
            "1. open": "27.2900",
            "2. high": "27.2900",
            "3. low": "27.1500",
            "4. close": "27.2200",
            "5. volume": "1163"
        },
        "2021-02-25": {
            "1. open": "27.3450",
            "2. high": "27.3450",
            "3. low": "26.5100",
            "4. close": "26.5100",
            "5. volume": "1286"
        },
        "2021-02-24": {
            "1. open": "27.4000",
            "2. high": "27.6700",
            "3. low": "27.3401",
            "4. close": "27.3401",
            "5. volume": "2600"
        },
        "2021-02-23": {
            "1. open": "27.4500",
            "2. high": "27.4500",
            "3. low": "27.1400",
            "4. close": "27.1500",
            "5. volume": "7452"
        },
        "2021-02-22": {
            "1. open": "27.1900",
            "2. high": "27.3500",
            "3. low": "27.1900",
            "4. close": "27.2000",
            "5. volume": "8913"
        },
        "2021-02-19": {
            "1. open": "27.5000",
            "2. high": "27.5000",
            "3. low": "27.3500",
            "4. close": "27.3500",
            "5. volume": "2175"
        },
        "2021-02-18": {
            "1. open": "27.3100",
            "2. high": "27.6700",
            "3. low": "27.0200",
            "4. close": "27.6700",
            "5. volume": "5702"
        },
        "2021-02-17": {
            "1. open": "27.5000",
            "2. high": "27.6700",
            "3. low": "27.1000",
            "4. close": "27.3500",
            "5. volume": "1924"
        },
        "2021-02-16": {
            "1. open": "27.0200",
            "2. high": "27.5500",
            "3. low": "27.0200",
            "4. close": "27.4500",
            "5. volume": "3499"
        },
        "2021-02-12": {
            "1. open": "27.4400",
            "2. high": "27.4400",
            "3. low": "27.2500",
            "4. close": "27.2500",
            "5. volume": "772"
        },
        "2021-02-11": {
            "1. open": "27.3750",
            "2. high": "27.4350",
            "3. low": "27.3750",
            "4. close": "27.4350",
            "5. volume": "6031"
        },
        "2021-02-10": {
            "1. open": "27.3500",
            "2. high": "27.4050",
            "3. low": "27.3240",
            "4. close": "27.4050",
            "5. volume": "4096"
        },
        "2021-02-09": {
            "1. open": "27.4500",
            "2. high": "27.4500",
            "3. low": "27.1500",
            "4. close": "27.1500",
            "5. volume": "988"
        },
        "2021-02-08": {
            "1. open": "27.4487",
            "2. high": "27.4487",
            "3. low": "27.4487",
            "4. close": "27.4487",
            "5. volume": "600"
        },
        "2021-02-05": {
            "1. open": "27.4700",
            "2. high": "27.6700",
            "3. low": "27.3000",
            "4. close": "27.6700",
            "5. volume": "2330"
        },
        "2021-02-04": {
            "1. open": "27.4100",
            "2. high": "27.4100",
            "3. low": "27.1501",
            "4. close": "27.1501",
            "5. volume": "3748"
        },
        "2021-02-03": {
            "1. open": "27.1001",
            "2. high": "27.1001",
            "3. low": "27.1001",
            "4. close": "27.1001",
            "5. volume": "72"
        },
        "2021-02-02": {
            "1. open": "27.5900",
            "2. high": "27.5900",
            "3. low": "27.1001",
            "4. close": "27.1001",
            "5. volume": "514"
        },
        "2021-02-01": {
            "1. open": "27.3050",
            "2. high": "27.5000",
            "3. low": "27.3050",
            "4. close": "27.5000",
            "5. volume": "2100"
        },
        "2021-01-29": {
            "1. open": "27.5700",
            "2. high": "27.5700",
            "3. low": "27.5700",
            "4. close": "27.5700",
            "5. volume": "1800"
        },
        "2021-01-28": {
            "1. open": "27.5000",
            "2. high": "27.5000",
            "3. low": "27.0200",
            "4. close": "27.3054",
            "5. volume": "3684"
        },
        "2021-01-27": {
            "1. open": "27.8500",
            "2. high": "27.8500",
            "3. low": "27.8500",
            "4. close": "27.8500",
            "5. volume": "701"
        },
        "2021-01-26": {
            "1. open": "27.8300",
            "2. high": "27.8500",
            "3. low": "27.8200",
            "4. close": "27.8500",
            "5. volume": "1202"
        },
        "2021-01-25": {
            "1. open": "27.7800",
            "2. high": "27.7800",
            "3. low": "27.5840",
            "4. close": "27.7800",
            "5. volume": "1912"
        },
        "2021-01-22": {
            "1. open": "27.7800",
            "2. high": "27.7800",
            "3. low": "27.7800",
            "4. close": "27.7800",
            "5. volume": "300"
        },
        "2021-01-21": {
            "1. open": "27.6400",
            "2. high": "27.7800",
            "3. low": "27.6400",
            "4. close": "27.6400",
            "5. volume": "945"
        },
        "2021-01-20": {
            "1. open": "27.5500",
            "2. high": "27.7800",
            "3. low": "27.4250",
            "4. close": "27.6400",
            "5. volume": "5280"
        },
        "2021-01-19": {
            "1. open": "27.5500",
            "2. high": "27.5500",
            "3. low": "27.5400",
            "4. close": "27.5500",
            "5. volume": "1625"
        },
        "2021-01-15": {
            "1. open": "27.7320",
            "2. high": "27.7320",
            "3. low": "27.5400",
            "4. close": "27.5400",
            "5. volume": "1012"
        },
        "2021-01-14": {
            "1. open": "27.4499",
            "2. high": "27.7800",
            "3. low": "27.4300",
            "4. close": "27.7800",
            "5. volume": "4325"
        },
        "2021-01-13": {
            "1. open": "27.6200",
            "2. high": "27.6200",
            "3. low": "27.4000",
            "4. close": "27.4000",
            "5. volume": "1605"
        },
        "2021-01-12": {
            "1. open": "27.4000",
            "2. high": "27.4700",
            "3. low": "27.4000",
            "4. close": "27.4700",
            "5. volume": "1846"
        },
        "2021-01-11": {
            "1. open": "27.6180",
            "2. high": "27.6180",
            "3. low": "27.6180",
            "4. close": "27.6180",
            "5. volume": "500"
        },
        "2021-01-08": {
            "1. open": "27.6500",
            "2. high": "27.6500",
            "3. low": "27.6100",
            "4. close": "27.6500",
            "5. volume": "890"
        },
        "2021-01-07": {
            "1. open": "27.3000",
            "2. high": "27.5400",
            "3. low": "27.3000",
            "4. close": "27.5400",
            "5. volume": "929"
        },
        "2021-01-06": {
            "1. open": "27.5949",
            "2. high": "27.5949",
            "3. low": "27.1400",
            "4. close": "27.1500",
            "5. volume": "1803"
        },
        "2021-01-05": {
            "1. open": "27.0601",
            "2. high": "27.1432",
            "3. low": "27.0601",
            "4. close": "27.1432",
            "5. volume": "502"
        },
        "2021-01-04": {
            "1. open": "27.5200",
            "2. high": "27.7800",
            "3. low": "27.0501",
            "4. close": "27.0501",
            "5. volume": "2040"
        },
        "2020-12-31": {
            "1. open": "27.5000",
            "2. high": "27.5200",
            "3. low": "27.5000",
            "4. close": "27.5200",
            "5. volume": "670"
        },
        "2020-12-30": {
            "1. open": "27.2800",
            "2. high": "27.7111",
            "3. low": "27.2800",
            "4. close": "27.5000",
            "5. volume": "2606"
        },
        "2020-12-29": {
            "1. open": "27.5000",
            "2. high": "27.5000",
            "3. low": "27.5000",
            "4. close": "27.5000",
            "5. volume": "42"
        },
        "2020-12-28": {
            "1. open": "27.5000",
            "2. high": "27.5000",
            "3. low": "27.5000",
            "4. close": "27.5000",
            "5. volume": "539"
        },
        "2020-12-24": {
            "1. open": "27.7800",
            "2. high": "27.7800",
            "3. low": "27.7800",
            "4. close": "27.7800",
            "5. volume": "565"
        },
        "2020-12-23": {
            "1. open": "27.4341",
            "2. high": "27.7800",
            "3. low": "27.4000",
            "4. close": "27.7800",
            "5. volume": "1706"
        },
        "2020-12-22": {
            "1. open": "27.2700",
            "2. high": "27.7800",
            "3. low": "27.0400",
            "4. close": "27.5000",
            "5. volume": "8997"
        },
        "2020-12-21": {
            "1. open": "27.6050",
            "2. high": "27.8500",
            "3. low": "27.6050",
            "4. close": "27.8000",
            "5. volume": "3674"
        },
        "2020-12-18": {
            "1. open": "27.8000",
            "2. high": "27.8500",
            "3. low": "27.8000",
            "4. close": "27.8500",
            "5. volume": "692"
        },
        "2020-12-17": {
            "1. open": "27.8000",
            "2. high": "27.8000",
            "3. low": "27.8000",
            "4. close": "27.8000",
            "5. volume": "8447"
        },
        "2020-12-16": {
            "1. open": "27.5000",
            "2. high": "27.7800",
            "3. low": "27.5000",
            "4. close": "27.7400",
            "5. volume": "5625"
        },
        "2020-12-15": {
            "1. open": "27.5900",
            "2. high": "27.6000",
            "3. low": "27.5001",
            "4. close": "27.6000",
            "5. volume": "6281"
        },
        "2020-12-14": {
            "1. open": "27.3000",
            "2. high": "27.6200",
            "3. low": "27.0710",
            "4. close": "27.6000",
            "5. volume": "6570"
        },
        "2020-12-11": {
            "1. open": "27.2400",
            "2. high": "27.3000",
            "3. low": "27.0200",
            "4. close": "27.3000",
            "5. volume": "5083"
        },
        "2020-12-10": {
            "1. open": "27.2500",
            "2. high": "27.2500",
            "3. low": "27.0200",
            "4. close": "27.2500",
            "5. volume": "3500"
        },
        "2020-12-09": {
            "1. open": "27.2400",
            "2. high": "27.2500",
            "3. low": "27.2400",
            "4. close": "27.2500",
            "5. volume": "2000"
        },
        "2020-12-08": {
            "1. open": "27.2000",
            "2. high": "27.2500",
            "3. low": "27.1400",
            "4. close": "27.1800",
            "5. volume": "4459"
        },
        "2020-12-07": {
            "1. open": "27.0450",
            "2. high": "27.2300",
            "3. low": "27.0450",
            "4. close": "27.2300",
            "5. volume": "2842"
        },
        "2020-12-04": {
            "1. open": "26.9800",
            "2. high": "26.9800",
            "3. low": "26.7300",
            "4. close": "26.9600",
            "5. volume": "6248"
        },
        "2020-12-03": {
            "1. open": "26.9800",
            "2. high": "26.9800",
            "3. low": "26.9750",
            "4. close": "26.9800",
            "5. volume": "1441"
        },
        "2020-12-02": {
            "1. open": "26.9800",
            "2. high": "26.9800",
            "3. low": "26.9650",
            "4. close": "26.9800",
            "5. volume": "5436"
        },
        "2020-12-01": {
            "1. open": "26.9900",
            "2. high": "26.9900",
            "3. low": "26.9235",
            "4. close": "26.9900",
            "5. volume": "8622"
        },
        "2020-11-30": {
            "1. open": "26.9899",
            "2. high": "27.1400",
            "3. low": "26.9899",
            "4. close": "27.1400",
            "5. volume": "3516"
        },
        "2020-11-27": {
            "1. open": "27.1390",
            "2. high": "27.1400",
            "3. low": "27.0000",
            "4. close": "27.0000",
            "5. volume": "5729"
        },
        "2020-11-25": {
            "1. open": "26.7250",
            "2. high": "27.1000",
            "3. low": "26.7250",
            "4. close": "27.1000",
            "5. volume": "3400"
        },
        "2020-11-24": {
            "1. open": "27.0500",
            "2. high": "27.0500",
            "3. low": "26.8600",
            "4. close": "26.9000",
            "5. volume": "10653"
        },
        "2020-11-23": {
            "1. open": "27.0500",
            "2. high": "27.0500",
            "3. low": "26.8000",
            "4. close": "26.9800",
            "5. volume": "6510"
        },
        "2020-11-20": {
            "1. open": "26.8700",
            "2. high": "27.0500",
            "3. low": "26.8700",
            "4. close": "26.9760",
            "5. volume": "5656"
        },
        "2020-11-19": {
            "1. open": "26.8600",
            "2. high": "26.8700",
            "3. low": "26.7350",
            "4. close": "26.7350",
            "5. volume": "2200"
        },
        "2020-11-18": {
            "1. open": "26.8000",
            "2. high": "26.8700",
            "3. low": "26.6200",
            "4. close": "26.8500",
            "5. volume": "7519"
        },
        "2020-11-17": {
            "1. open": "26.8100",
            "2. high": "26.8400",
            "3. low": "26.5000",
            "4. close": "26.8400",
            "5. volume": "4591"
        },
        "2020-11-16": {
            "1. open": "26.5500",
            "2. high": "26.8400",
            "3. low": "26.5500",
            "4. close": "26.8400",
            "5. volume": "21598"
        },
        "2020-11-13": {
            "1. open": "26.5498",
            "2. high": "26.6485",
            "3. low": "26.2800",
            "4. close": "26.4500",
            "5. volume": "44867"
        },
        "2020-11-12": {
            "1. open": "26.6000",
            "2. high": "26.6000",
            "3. low": "26.2600",
            "4. close": "26.5500",
            "5. volume": "16339"
        },
        "2020-11-11": {
            "1. open": "26.6500",
            "2. high": "27.0500",
            "3. low": "26.6500",
            "4. close": "27.0500",
            "5. volume": "5235"
        },
        "2020-11-10": {
            "1. open": "26.5500",
            "2. high": "26.5500",
            "3. low": "26.2100",
            "4. close": "26.5500",
            "5. volume": "5948"
        },
        "2020-11-09": {
            "1. open": "26.3500",
            "2. high": "26.5500",
            "3. low": "26.2100",
            "4. close": "26.5500",
            "5. volume": "16704"
        },
        "2020-11-06": {
            "1. open": "26.4999",
            "2. high": "26.4999",
            "3. low": "26.4000",
            "4. close": "26.4556",
            "5. volume": "1009"
        },
        "2020-11-05": {
            "1. open": "26.4900",
            "2. high": "26.4900",
            "3. low": "26.2400",
            "4. close": "26.2400",
            "5. volume": "22622"
        },
        "2020-11-04": {
            "1. open": "26.5500",
            "2. high": "26.5500",
            "3. low": "26.1700",
            "4. close": "26.3800",
            "5. volume": "19714"
        },
        "2020-11-03": {
            "1. open": "26.5000",
            "2. high": "26.5500",
            "3. low": "26.2000",
            "4. close": "26.5500",
            "5. volume": "11380"
        },
        "2020-11-02": {
            "1. open": "26.3250",
            "2. high": "26.5500",
            "3. low": "26.0900",
            "4. close": "26.5500",
            "5. volume": "12950"
        },
        "2020-10-30": {
            "1. open": "26.4182",
            "2. high": "26.5500",
            "3. low": "26.0900",
            "4. close": "26.0939",
            "5. volume": "8962"
        },
        "2020-10-29": {
            "1. open": "26.7000",
            "2. high": "26.7000",
            "3. low": "26.4500",
            "4. close": "26.5500",
            "5. volume": "24744"
        },
        "2020-10-28": {
            "1. open": "26.6000",
            "2. high": "26.9800",
            "3. low": "26.6000",
            "4. close": "26.6600",
            "5. volume": "37310"
        },
        "2020-10-27": {
            "1. open": "26.6000",
            "2. high": "27.0500",
            "3. low": "26.5000",
            "4. close": "26.6000",
            "5. volume": "74696"
        },
        "2020-10-26": {
            "1. open": "27.0900",
            "2. high": "27.0900",
            "3. low": "26.6000",
            "4. close": "26.6000",
            "5. volume": "35557"
        },
        "2020-10-23": {
            "1. open": "27.0500",
            "2. high": "27.0500",
            "3. low": "26.7000",
            "4. close": "26.7000",
            "5. volume": "500"
        },
        "2020-10-22": {
            "1. open": "26.4701",
            "2. high": "26.4850",
            "3. low": "26.4701",
            "4. close": "26.4850",
            "5. volume": "550"
        },
        "2020-10-21": {
            "1. open": "26.5200",
            "2. high": "26.5200",
            "3. low": "26.4701",
            "4. close": "26.4701",
            "5. volume": "602"
        },
        "2020-10-20": {
            "1. open": "27.0500",
            "2. high": "27.0500",
            "3. low": "26.9300",
            "4. close": "27.0500",
            "5. volume": "800"
        },
        "2020-10-19": {
            "1. open": "26.7500",
            "2. high": "26.7500",
            "3. low": "26.5600",
            "4. close": "26.7495",
            "5. volume": "560"
        },
        "2020-10-16": {
            "1. open": "27.0100",
            "2. high": "27.0400",
            "3. low": "26.5500",
            "4. close": "26.9750",
            "5. volume": "1000"
        },
        "2020-10-15": {
            "1. open": "26.5000",
            "2. high": "26.9800",
            "3. low": "26.4700",
            "4. close": "26.5500",
            "5. volume": "2298"
        },
        "2020-10-14": {
            "1. open": "26.6500",
            "2. high": "26.8391",
            "3. low": "26.6500",
            "4. close": "26.8391",
            "5. volume": "465"
        },
        "2020-10-13": {
            "1. open": "26.6500",
            "2. high": "26.6500",
            "3. low": "26.6500",
            "4. close": "26.6500",
            "5. volume": "27"
        },
        "2020-10-12": {
            "1. open": "26.6500",
            "2. high": "26.6500",
            "3. low": "26.6500",
            "4. close": "26.6500",
            "5. volume": "0"
        },
        "2020-10-09": {
            "1. open": "26.6500",
            "2. high": "26.6500",
            "3. low": "26.6500",
            "4. close": "26.6500",
            "5. volume": "300"
        },
        "2020-10-08": {
            "1. open": "26.7300",
            "2. high": "26.7300",
            "3. low": "26.7300",
            "4. close": "26.7300",
            "5. volume": "400"
        },
        "2020-10-07": {
            "1. open": "26.7550",
            "2. high": "27.0300",
            "3. low": "26.7550",
            "4. close": "26.9605",
            "5. volume": "700"
        },
        "2020-10-06": {
            "1. open": "26.5200",
            "2. high": "26.6024",
            "3. low": "26.4900",
            "4. close": "26.5000",
            "5. volume": "1400"
        },
        "2020-10-05": {
            "1. open": "27.0000",
            "2. high": "27.0000",
            "3. low": "27.0000",
            "4. close": "27.0000",
            "5. volume": "10"
        },
        "2020-10-02": {
            "1. open": "26.8405",
            "2. high": "27.0100",
            "3. low": "26.8405",
            "4. close": "27.0000",
            "5. volume": "400"
        },
        "2020-10-01": {
            "1. open": "26.6410",
            "2. high": "26.6410",
            "3. low": "26.6410",
            "4. close": "26.6410",
            "5. volume": "600"
        },
        "2020-09-30": {
            "1. open": "26.7100",
            "2. high": "26.9830",
            "3. low": "26.7100",
            "4. close": "26.9136",
            "5. volume": "3914"
        },
        "2020-09-29": {
            "1. open": "26.7200",
            "2. high": "26.7200",
            "3. low": "26.6500",
            "4. close": "26.6500",
            "5. volume": "1600"
        },
        "2020-09-28": {
            "1. open": "26.5850",
            "2. high": "26.5870",
            "3. low": "26.5725",
            "4. close": "26.5870",
            "5. volume": "600"
        },
        "2020-09-25": {
            "1. open": "26.3700",
            "2. high": "26.6300",
            "3. low": "26.3700",
            "4. close": "26.5400",
            "5. volume": "586"
        },
        "2020-09-24": {
            "1. open": "26.4700",
            "2. high": "26.7200",
            "3. low": "26.4700",
            "4. close": "26.7200",
            "5. volume": "600"
        },
        "2020-09-23": {
            "1. open": "27.0400",
            "2. high": "27.0400",
            "3. low": "26.4965",
            "4. close": "26.4965",
            "5. volume": "4361"
        },
        "2020-09-22": {
            "1. open": "27.0500",
            "2. high": "27.0500",
            "3. low": "27.0500",
            "4. close": "27.0500",
            "5. volume": "2"
        },
        "2020-09-21": {
            "1. open": "26.7100",
            "2. high": "27.0500",
            "3. low": "26.3700",
            "4. close": "27.0500",
            "5. volume": "4022"
        },
        "2020-09-18": {
            "1. open": "26.7800",
            "2. high": "26.8000",
            "3. low": "26.5154",
            "4. close": "26.5154",
            "5. volume": "900"
        },
        "2020-09-17": {
            "1. open": "26.3800",
            "2. high": "26.7000",
            "3. low": "26.3800",
            "4. close": "26.7000",
            "5. volume": "2701"
        },
        "2020-09-16": {
            "1. open": "26.6200",
            "2. high": "26.6498",
            "3. low": "26.4500",
            "4. close": "26.4500",
            "5. volume": "3033"
        },
        "2020-09-15": {
            "1. open": "26.7700",
            "2. high": "27.0900",
            "3. low": "26.4200",
            "4. close": "26.4200",
            "5. volume": "4400"
        },
        "2020-09-14": {
            "1. open": "26.5000",
            "2. high": "26.5000",
            "3. low": "26.5000",
            "4. close": "26.5000",
            "5. volume": "27"
        },
        "2020-09-11": {
            "1. open": "26.6101",
            "2. high": "26.6900",
            "3. low": "26.5000",
            "4. close": "26.5000",
            "5. volume": "1800"
        },
        "2020-09-10": {
            "1. open": "27.0600",
            "2. high": "27.0900",
            "3. low": "27.0600",
            "4. close": "27.0900",
            "5. volume": "870"
        },
        "2020-09-09": {
            "1. open": "26.5800",
            "2. high": "26.9000",
            "3. low": "26.5100",
            "4. close": "26.6100",
            "5. volume": "6636"
        },
        "2020-09-08": {
            "1. open": "26.3700",
            "2. high": "26.5500",
            "3. low": "26.3700",
            "4. close": "26.4851",
            "5. volume": "9090"
        },
        "2020-09-04": {
            "1. open": "26.5000",
            "2. high": "26.5000",
            "3. low": "26.4000",
            "4. close": "26.4987",
            "5. volume": "7196"
        },
        "2020-09-03": {
            "1. open": "26.4500",
            "2. high": "26.4600",
            "3. low": "26.3250",
            "4. close": "26.4500",
            "5. volume": "4651"
        },
        "2020-09-02": {
            "1. open": "26.4500",
            "2. high": "26.5000",
            "3. low": "26.3535",
            "4. close": "26.4500",
            "5. volume": "10200"
        },
        "2020-09-01": {
            "1. open": "26.3700",
            "2. high": "26.4800",
            "3. low": "26.1450",
            "4. close": "26.2500",
            "5. volume": "8566"
        },
        "2020-08-31": {
            "1. open": "26.4000",
            "2. high": "26.4000",
            "3. low": "26.1300",
            "4. close": "26.1300",
            "5. volume": "564"
        },
        "2020-08-28": {
            "1. open": "26.1800",
            "2. high": "26.2000",
            "3. low": "26.0800",
            "4. close": "26.1000",
            "5. volume": "12682"
        },
        "2020-08-27": {
            "1. open": "26.4000",
            "2. high": "26.4000",
            "3. low": "26.4000",
            "4. close": "26.4000",
            "5. volume": "1010"
        },
        "2020-08-26": {
            "1. open": "26.4100",
            "2. high": "26.4100",
            "3. low": "26.4100",
            "4. close": "26.4100",
            "5. volume": "502"
        },
        "2020-08-25": {
            "1. open": "26.2982",
            "2. high": "26.3499",
            "3. low": "26.2700",
            "4. close": "26.3400",
            "5. volume": "1016"
        },
        "2020-08-24": {
            "1. open": "26.2500",
            "2. high": "26.2500",
            "3. low": "26.0000",
            "4. close": "26.0600",
            "5. volume": "6502"
        },
        "2020-08-21": {
            "1. open": "26.0300",
            "2. high": "26.1400",
            "3. low": "26.0300",
            "4. close": "26.1400",
            "5. volume": "498"
        },
        "2020-08-20": {
            "1. open": "26.1400",
            "2. high": "26.1400",
            "3. low": "26.1400",
            "4. close": "26.1400",
            "5. volume": "415"
        },
        "2020-08-19": {
            "1. open": "26.2400",
            "2. high": "26.2500",
            "3. low": "26.1845",
            "4. close": "26.2500",
            "5. volume": "4100"
        },
        "2020-08-18": {
            "1. open": "26.2499",
            "2. high": "26.2500",
            "3. low": "25.9600",
            "4. close": "25.9600",
            "5. volume": "3729"
        },
        "2020-08-17": {
            "1. open": "25.9505",
            "2. high": "26.4700",
            "3. low": "25.9505",
            "4. close": "26.0100",
            "5. volume": "8932"
        },
        "2020-08-14": {
            "1. open": "25.9100",
            "2. high": "26.2300",
            "3. low": "25.9000",
            "4. close": "25.9500",
            "5. volume": "12483"
        },
        "2020-08-13": {
            "1. open": "26.0100",
            "2. high": "26.0100",
            "3. low": "25.8100",
            "4. close": "26.0000",
            "5. volume": "4215"
        },
        "2020-08-12": {
            "1. open": "25.9950",
            "2. high": "26.0000",
            "3. low": "25.9950",
            "4. close": "26.0000",
            "5. volume": "2000"
        },
        "2020-08-11": {
            "1. open": "26.1800",
            "2. high": "26.1850",
            "3. low": "26.1700",
            "4. close": "26.1800",
            "5. volume": "2000"
        },
        "2020-08-10": {
            "1. open": "26.1600",
            "2. high": "26.1640",
            "3. low": "25.7600",
            "4. close": "25.7700",
            "5. volume": "5822"
        },
        "2020-08-07": {
            "1. open": "26.1600",
            "2. high": "26.1600",
            "3. low": "26.1600",
            "4. close": "26.1600",
            "5. volume": "4000"
        },
        "2020-08-06": {
            "1. open": "26.2000",
            "2. high": "26.2580",
            "3. low": "26.1600",
            "4. close": "26.2000",
            "5. volume": "2570"
        },
        "2020-08-05": {
            "1. open": "26.2000",
            "2. high": "26.3250",
            "3. low": "26.2000",
            "4. close": "26.2000",
            "5. volume": "1858"
        },
        "2020-08-04": {
            "1. open": "26.3250",
            "2. high": "26.3250",
            "3. low": "26.2500",
            "4. close": "26.2800",
            "5. volume": "2803"
        },
        "2020-08-03": {
            "1. open": "26.1800",
            "2. high": "26.1800",
            "3. low": "26.1600",
            "4. close": "26.1600",
            "5. volume": "1100"
        },
        "2020-07-31": {
            "1. open": "26.3800",
            "2. high": "26.4007",
            "3. low": "25.5600",
            "4. close": "26.1100",
            "5. volume": "4555"
        },
        "2020-07-30": {
            "1. open": "26.4000",
            "2. high": "26.5000",
            "3. low": "26.3800",
            "4. close": "26.3800",
            "5. volume": "3085"
        },
        "2020-07-29": {
            "1. open": "26.2000",
            "2. high": "26.5000",
            "3. low": "26.2000",
            "4. close": "26.3800",
            "5. volume": "6543"
        },
        "2020-07-28": {
            "1. open": "26.0756",
            "2. high": "26.2000",
            "3. low": "26.0756",
            "4. close": "26.2000",
            "5. volume": "3433"
        },
        "2020-07-27": {
            "1. open": "26.0690",
            "2. high": "26.1000",
            "3. low": "26.0050",
            "4. close": "26.1000",
            "5. volume": "5686"
        },
        "2020-07-24": {
            "1. open": "26.0000",
            "2. high": "26.1100",
            "3. low": "26.0000",
            "4. close": "26.1100",
            "5. volume": "24706"
        },
        "2020-07-23": {
            "1. open": "26.0000",
            "2. high": "26.0200",
            "3. low": "25.9000",
            "4. close": "25.9000",
            "5. volume": "6201"
        },
        "2020-07-22": {
            "1. open": "25.9215",
            "2. high": "26.0000",
            "3. low": "25.7600",
            "4. close": "26.0000",
            "5. volume": "10200"
        },
        "2020-07-21": {
            "1. open": "25.9100",
            "2. high": "25.9980",
            "3. low": "25.8250",
            "4. close": "25.9060",
            "5. volume": "9451"
        },
        "2020-07-20": {
            "1. open": "25.9000",
            "2. high": "25.9150",
            "3. low": "25.8850",
            "4. close": "25.9150",
            "5. volume": "3072"
        },
        "2020-07-17": {
            "1. open": "25.8330",
            "2. high": "25.8330",
            "3. low": "25.6500",
            "4. close": "25.6500",
            "5. volume": "749"
        },
        "2020-07-16": {
            "1. open": "25.8300",
            "2. high": "25.9200",
            "3. low": "25.6500",
            "4. close": "25.7650",
            "5. volume": "6140"
        },
        "2020-07-15": {
            "1. open": "25.9500",
            "2. high": "25.9600",
            "3. low": "25.8300",
            "4. close": "25.8500",
            "5. volume": "4632"
        },
        "2020-07-14": {
            "1. open": "25.9120",
            "2. high": "25.9800",
            "3. low": "25.8800",
            "4. close": "25.9200",
            "5. volume": "4910"
        },
        "2020-07-13": {
            "1. open": "25.9800",
            "2. high": "25.9800",
            "3. low": "25.8900",
            "4. close": "25.9600",
            "5. volume": "5000"
        },
        "2020-07-10": {
            "1. open": "25.9000",
            "2. high": "25.9500",
            "3. low": "25.7970",
            "4. close": "25.9500",
            "5. volume": "5546"
        },
        "2020-07-09": {
            "1. open": "25.7500",
            "2. high": "25.9850",
            "3. low": "25.7500",
            "4. close": "25.8780",
            "5. volume": "4025"
        },
        "2020-07-08": {
            "1. open": "25.9870",
            "2. high": "25.9900",
            "3. low": "25.8700",
            "4. close": "25.9120",
            "5. volume": "1200"
        },
        "2020-07-07": {
            "1. open": "25.9000",
            "2. high": "25.9800",
            "3. low": "25.8300",
            "4. close": "25.9800",
            "5. volume": "43308"
        },
        "2020-07-06": {
            "1. open": "25.7100",
            "2. high": "25.8800",
            "3. low": "25.7100",
            "4. close": "25.8500",
            "5. volume": "7200"
        },
        "2020-07-02": {
            "1. open": "25.8000",
            "2. high": "25.9800",
            "3. low": "25.7500",
            "4. close": "25.8000",
            "5. volume": "14246"
        },
        "2020-07-01": {
            "1. open": "25.6700",
            "2. high": "25.7000",
            "3. low": "25.6000",
            "4. close": "25.7000",
            "5. volume": "2202"
        },
        "2020-06-30": {
            "1. open": "25.7700",
            "2. high": "25.7800",
            "3. low": "25.6900",
            "4. close": "25.6900",
            "5. volume": "15291"
        },
        "2020-06-29": {
            "1. open": "25.8900",
            "2. high": "25.8900",
            "3. low": "25.7000",
            "4. close": "25.7225",
            "5. volume": "6662"
        },
        "2020-06-26": {
            "1. open": "25.8900",
            "2. high": "25.8900",
            "3. low": "25.7160",
            "4. close": "25.8110",
            "5. volume": "3290"
        },
        "2020-06-25": {
            "1. open": "25.8000",
            "2. high": "25.8900",
            "3. low": "25.6800",
            "4. close": "25.8700",
            "5. volume": "10127"
        },
        "2020-06-24": {
            "1. open": "25.7200",
            "2. high": "25.8500",
            "3. low": "25.6950",
            "4. close": "25.8500",
            "5. volume": "7317"
        },
        "2020-06-23": {
            "1. open": "25.8350",
            "2. high": "25.9100",
            "3. low": "25.8350",
            "4. close": "25.9100",
            "5. volume": "1584"
        },
        "2020-06-22": {
            "1. open": "25.9400",
            "2. high": "25.9400",
            "3. low": "25.7300",
            "4. close": "25.8400",
            "5. volume": "6933"
        },
        "2020-06-19": {
            "1. open": "25.6900",
            "2. high": "25.7000",
            "3. low": "25.5000",
            "4. close": "25.7000",
            "5. volume": "3400"
        },
        "2020-06-18": {
            "1. open": "25.9000",
            "2. high": "25.9000",
            "3. low": "25.6300",
            "4. close": "25.7000",
            "5. volume": "4898"
        },
        "2020-06-17": {
            "1. open": "25.7500",
            "2. high": "25.8150",
            "3. low": "25.5710",
            "4. close": "25.8150",
            "5. volume": "1385"
        },
        "2020-06-16": {
            "1. open": "25.8500",
            "2. high": "25.9000",
            "3. low": "25.7000",
            "4. close": "25.7500",
            "5. volume": "2800"
        },
        "2020-06-15": {
            "1. open": "25.3500",
            "2. high": "25.6800",
            "3. low": "25.3500",
            "4. close": "25.6800",
            "5. volume": "1373"
        },
        "2020-06-12": {
            "1. open": "25.6600",
            "2. high": "25.6600",
            "3. low": "25.6500",
            "4. close": "25.6500",
            "5. volume": "1000"
        },
        "2020-06-11": {
            "1. open": "25.8390",
            "2. high": "25.9800",
            "3. low": "25.5000",
            "4. close": "25.5900",
            "5. volume": "5810"
        },
        "2020-06-10": {
            "1. open": "26.0400",
            "2. high": "26.0500",
            "3. low": "26.0000",
            "4. close": "26.0250",
            "5. volume": "17813"
        },
        "2020-06-09": {
            "1. open": "25.8750",
            "2. high": "26.0500",
            "3. low": "25.8750",
            "4. close": "25.9700",
            "5. volume": "4425"
        },
        "2020-06-08": {
            "1. open": "26.2400",
            "2. high": "26.2400",
            "3. low": "26.0250",
            "4. close": "26.0500",
            "5. volume": "7820"
        },
        "2020-06-05": {
            "1. open": "25.7500",
            "2. high": "26.2000",
            "3. low": "25.6600",
            "4. close": "26.0750",
            "5. volume": "22874"
        },
        "2020-06-04": {
            "1. open": "25.7500",
            "2. high": "26.0000",
            "3. low": "25.6930",
            "4. close": "25.9250",
            "5. volume": "16175"
        },
        "2020-06-03": {
            "1. open": "25.7500",
            "2. high": "25.8000",
            "3. low": "25.6000",
            "4. close": "25.6990",
            "5. volume": "16755"
        },
        "2020-06-02": {
            "1. open": "25.8000",
            "2. high": "25.8000",
            "3. low": "25.6800",
            "4. close": "25.7500",
            "5. volume": "23291"
        },
        "2020-06-01": {
            "1. open": "25.6980",
            "2. high": "25.7000",
            "3. low": "25.5670",
            "4. close": "25.7000",
            "5. volume": "20338"
        },
        "2020-05-29": {
            "1. open": "25.6800",
            "2. high": "25.7900",
            "3. low": "25.6250",
            "4. close": "25.6250",
            "5. volume": "22324"
        },
        "2020-05-28": {
            "1. open": "25.5900",
            "2. high": "25.7450",
            "3. low": "25.5900",
            "4. close": "25.7000",
            "5. volume": "22902"
        },
        "2020-05-27": {
            "1. open": "25.3750",
            "2. high": "25.4500",
            "3. low": "25.3400",
            "4. close": "25.4500",
            "5. volume": "42308"
        },
        "2020-05-26": {
            "1. open": "25.3350",
            "2. high": "25.5000",
            "3. low": "25.3100",
            "4. close": "25.4800",
            "5. volume": "7039"
        },
        "2020-05-22": {
            "1. open": "25.2700",
            "2. high": "25.3900",
            "3. low": "25.2500",
            "4. close": "25.2500",
            "5. volume": "3012"
        },
        "2020-05-21": {
            "1. open": "25.2600",
            "2. high": "25.4600",
            "3. low": "25.2500",
            "4. close": "25.2700",
            "5. volume": "17448"
        },
        "2020-05-20": {
            "1. open": "25.4000",
            "2. high": "25.4800",
            "3. low": "25.1800",
            "4. close": "25.2630",
            "5. volume": "19213"
        },
        "2020-05-19": {
            "1. open": "25.1500",
            "2. high": "25.4400",
            "3. low": "25.1500",
            "4. close": "25.3000",
            "5. volume": "11357"
        },
        "2020-05-18": {
            "1. open": "25.1500",
            "2. high": "25.1500",
            "3. low": "25.1000",
            "4. close": "25.1500",
            "5. volume": "10437"
        },
        "2020-05-15": {
            "1. open": "25.0000",
            "2. high": "25.1000",
            "3. low": "24.9400",
            "4. close": "25.0500",
            "5. volume": "14199"
        },
        "2020-05-14": {
            "1. open": "24.9700",
            "2. high": "25.1000",
            "3. low": "24.5000",
            "4. close": "25.0500",
            "5. volume": "32387"
        },
        "2020-05-13": {
            "1. open": "25.0940",
            "2. high": "25.1500",
            "3. low": "24.9500",
            "4. close": "24.9500",
            "5. volume": "15648"
        },
        "2020-05-12": {
            "1. open": "25.3200",
            "2. high": "25.3400",
            "3. low": "25.1300",
            "4. close": "25.1300",
            "5. volume": "24420"
        },
        "2020-05-11": {
            "1. open": "25.1400",
            "2. high": "25.2900",
            "3. low": "25.0900",
            "4. close": "25.2500",
            "5. volume": "37836"
        },
        "2020-05-08": {
            "1. open": "25.1000",
            "2. high": "25.2000",
            "3. low": "25.0000",
            "4. close": "25.1300",
            "5. volume": "50712"
        },
        "2020-05-05": {
            "1. open": "24.7700",
            "2. high": "24.8200",
            "3. low": "24.6540",
            "4. close": "24.8000",
            "5. volume": "144000"
        }
    }
}